audiocat_clark/__init__.py
audiocat_clark/audiocat
audiocat_clark/audiocat.png
audiocat_clark/audiocat.py
audiocat_clark/gpg.src
audiocat_clark/gpgappend.src
audiocat_clark/gui.py
audiocat_clark/install_dependencies.sh
audiocat_clark/killaudiocat.sh
audiocat_clark/mmack.sh
audiocat_clark/mmdata.sh
audiocat_clark/mmrx.py
audiocat_clark/mmrx.sh
audiocat_clark/mmrxnopwd.sh
audiocat_clark/mmshellout.sh
audiocat_clark/mmtx.sh
audiocat_clark/mmtxfile.sh
audiocat_clark/mute_mic.sh
audiocat_clark/restore_mic.sh
audiocat_clark/rx.src
audiocat_clark/stt.sh
audiocat_clark/tts.sh
audiocat_clark/tx.src
audiocat_clark/version
audiocat_clark/cfg/armor
audiocat_clark/cfg/baud
audiocat_clark/cfg/cipher_algo
audiocat_clark/cfg/confidence
audiocat_clark/cfg/end_msg
audiocat_clark/cfg/half_duplex
audiocat_clark/cfg/install_dependencies
audiocat_clark/cfg/interface_index_stt_in
audiocat_clark/cfg/interface_index_tts_out
audiocat_clark/cfg/keepalive_time_sec
audiocat_clark/cfg/limit
audiocat_clark/cfg/log_to_file
audiocat_clark/cfg/logging_level
audiocat_clark/cfg/max_retransmissions
audiocat_clark/cfg/need_ack
audiocat_clark/cfg/preamble
audiocat_clark/cfg/probe_msg
audiocat_clark/cfg/probe_sleep
audiocat_clark/cfg/redundant_transmissions
audiocat_clark/cfg/retransmission_timeout_sec
audiocat_clark/cfg/send_delay_sec
audiocat_clark/cfg/show_rx_prompt
audiocat_clark/cfg/show_tx_prompt
audiocat_clark/cfg/speech_to_text
audiocat_clark/cfg/split_tx_lines
audiocat_clark/cfg/start_msg
audiocat_clark/cfg/syncbyte
audiocat_clark/cfg/terminal
audiocat_clark/cfg/text_to_speech
audiocat_clark/cfg/timeout_poll_sec
audiocat_clark/cfg/tmp_path
audiocat_clark/cfg/trailer
audiocat_clark/cfg/verbose
audiocat_clark/cfg/volume_microphone
audiocat_clark/cfg/volume_speaker_left
audiocat_clark/cfg/volume_speaker_right
audiocat_clark/cfg/volume_stt_in
audiocat_clark/cfg/volume_tts_out
audiocat_clark/out/dummy
audiocat_clark/rx_files/dummy
audiocat_clark/state/rx_receiving_file
audiocat_clark/state/seq_rx
audiocat_clark-0.11.dist-info/LICENSE
audiocat_clark-0.11.dist-info/METADATA
audiocat_clark-0.11.dist-info/WHEEL
audiocat_clark-0.11.dist-info/entry_points.txt
audiocat_clark-0.11.dist-info/top_level.txt
audiocat_clark-0.11.dist-info/RECORD
