Metadata-Version: 2.1
Name: audiocat_clark
Version: 0.11
Summary: Encrypted audio tunnel for secure chat, file transfer and remote shell on Linux.
Home-page: https://github.com/ClarkFieseln/audiocat
Author: Clark Fieseln
Author-email: 
License: MIT
Project-URL: Source, https://github.com/ClarkFieseln/audiocat
Keywords: chat,messenger,remote shell,remote control,reverse shell,file transfer,modem,audio,cryptography,encryption,security,cybersecurity,linux,gpg,minimodem,e2ee,data diode
Classifier: License :: OSI Approved :: MIT License
Classifier: Programming Language :: Python :: 3.6
Classifier: Programming Language :: Python :: 3.7
Classifier: Programming Language :: Python :: 3.8
Classifier: Programming Language :: Python :: 3.9
Classifier: Development Status :: 5 - Production/Stable
Classifier: Environment :: Console
Classifier: Intended Audience :: End Users/Desktop
Classifier: Intended Audience :: Developers
Classifier: Operating System :: POSIX :: Linux
Classifier: Topic :: Security
License-File: LICENSE
